[
  {
    "word": "philu",
    "gloss": "sweetheart",
    "ipa": "/ˈɸi.lu/",
    "syllables": [
      "phi",
      "lu"
    ],
    "pos": [
      "noun",
      "adjective"
    ],
    "concept": "Sweetheart / Tender Dear",
    "description": "One who brings sweetness and light to daily life through affection. Sweetheart encompasses gentle romance, everyday tenderness, pet names and small gestures, and the understanding that sweetness sustains love.",
    "rationale": "The word 'philu' combines aspirated 'phi' with flowing 'lu'. Using only a fricative digraph, this pairing captures sweethearts as breath-filled affection flowing through time.",
    "pillars": [
      "art-nouveau"
    ],
    "tags": [
      "Community & Relationships",
      "Tender Dear",
      "Daily Sweetness",
      "Gentle Romance",
      "Everyday Tenderness",
      "Pet Names",
      "Small Gestures",
      "Sustaining Love"
    ]
  }
]