[
  {
    "word": "shialo",
    "gloss": "beauty",
    "ipa": "/ʃi.ˈa.lo/",
    "syllables": [
      "shi",
      "a",
      "lo"
    ],
    "pos": [
      "noun",
      "adjective"
    ],
    "concept": "Beauty / Aesthetic Harmony",
    "description": "The quality that evokes deep appreciation through form, pattern, or presence. Beauty encompasses visual grace, natural elegance, and the recognition of harmonious proportion - whether in a flower's spiral, a crafted object, or a kind gesture.",
    "rationale": "The word 'shialo' begins with the soft fricative 'shi', suggesting something delicate and refined. The vowel sequence 'i-a' creates an opening, like beauty revealing itself, while 'lo' provides a flowing conclusion. This three-syllable structure mirrors beauty's complexity - never simple, always unfolding.",
    "pillars": [
      "art-nouveau"
    ],
    "tags": [
      "Abstract Qualities",
      "Aesthetic Experience",
      "Visual Harmony",
      "Natural Forms",
      "Art & Creation",
      "Appreciation",
      "Sensory Perception"
    ]
  }
]