[
  {
    "word": "lenu",
    "gloss": "tolerance",
    "ipa": "/ˈle.nu/",
    "syllables": [
      "le",
      "nu"
    ],
    "pos": [
      "noun",
      "verb",
      "adjective"
    ],
    "concept": "Tolerance / Patient Acceptance",
    "description": "The practice of accepting differences with patience and grace, creating space for diverse ways of being. Tolerance encompasses bearing discomfort without reaction, allowing others their path, the strength to hold space for what we don't understand, and the wisdom that diversity enriches community.",
    "rationale": "The word 'lenu' combines the gentle, allowing 'le' with the grounded stability of 'nu'. This pairing suggests soft strength - tolerance not as weakness but as the power to remain stable while allowing difference. The flowing sounds reflect tolerance's graceful nature.",
    "pillars": [
      "peace-linguistics",
      "buddhist"
    ],
    "tags": [
      "Abstract Qualities",
      "Patient Acceptance",
      "Diversity Embrace",
      "Allowing Difference",
      "Gentle Strength",
      "Space Holding",
      "Non-reactive Presence",
      "Community Enrichment"
    ]
  }
]