[
  {
    "word": "shiluma",
    "gloss": "tranquility",
    "ipa": "/ʃi.ˈlu.ma/",
    "syllables": [
      "shi",
      "lu",
      "ma"
    ],
    "pos": [
      "noun",
      "adjective"
    ],
    "concept": "Tranquility / Deep Calm",
    "description": "A state of profound calm and unruffled peace, like still water reflecting sky. Tranquility encompasses freedom from agitation, the deep rest found in acceptance, meditative stillness that remains undisturbed by external conditions, and the serene strength of a quiet mind.",
    "rationale": "The word 'shiluma' begins with the hushed 'shi', flows through the liquid 'lu', and settles into the grounded 'ma'. This three-syllable journey mirrors tranquility's deepening - from surface quiet through flowing calm to embodied peace. Each syllable adds depth to the stillness.",
    "pillars": [
      "buddhist"
    ],
    "tags": [
      "Abstract Qualities",
      "Deep Calm",
      "Profound Peace",
      "Meditative Stillness",
      "Unruffled State",
      "Serene Strength",
      "Inner Quiet",
      "Settled Mind"
    ]
  }
]