[
  {
    "word": "phelo",
    "gloss": "virtue",
    "ipa": "/ˈɸe.lo/",
    "syllables": [
      "phe",
      "lo"
    ],
    "pos": [
      "noun",
      "adjective"
    ],
    "concept": "Virtue / Moral Excellence",
    "description": "The cultivation of qualities that contribute to ethical living and collective wellbeing. Virtue encompasses right action, skillful means, the development of noble characteristics, and the embodiment of values that create harmony in communities.",
    "rationale": "The word 'phelo' begins with the aspirated 'phe', like virtue breathing life into action. The flowing 'lo' suggests continuity and wholeness - virtue not as rigid rule but as living practice. The fricative opening gives the word a quality of mindful intention.",
    "pillars": [
      "peace-linguistics",
      "buddhist"
    ],
    "tags": [
      "Abstract Qualities",
      "Moral Excellence",
      "Ethical Living",
      "Right Action",
      "Skillful Means",
      "Character Development",
      "Noble Qualities",
      "Community Values"
    ]
  }
]