[
  {
    "word": "hiu",
    "gloss": "rhythm",
    "ipa": "/ˈhi.u/",
    "syllables": [
      "hi",
      "u"
    ],
    "pos": [
      "noun",
      "verb"
    ],
    "concept": "Rhythm / Time Dance",
    "description": "The patterned flow of sound and silence that gives life to language and music. Rhythm encompasses natural cadence, the heartbeat of expression, communal synchronization, and the understanding that rhythm connects us to the pulse of existence.",
    "rationale": "The word 'hiu' combines aspirated 'hi' with rounded 'u', creating vowel hiatus only. This breath-to-completion structure captures rhythm as the living pulse of communication.",
    "pillars": [
      "pre-industrial"
    ],
    "tags": [
      "Communication & Expression",
      "Time Dance",
      "Patterned Flow",
      "Sound-Silence Pattern",
      "Natural Cadence",
      "Expression Heartbeat",
      "Communal Sync",
      "Existence Pulse",
      "Living Pattern"
    ]
  }
]