[
  {
    "word": "rema",
    "gloss": "drop",
    "ipa": "/ˈre.ma/",
    "syllables": [
      "re",
      "ma"
    ],
    "pos": [
      "verb"
    ],
    "concept": "Drop / Let Fall",
    "description": "To let something fall or release it downward. Dropping encompasses releasing hold, gravity taking over, surrender to earth, letting be.",
    "rationale": "The word 'rema' combines returning 're' with maternal 'ma'. This return-to-earth structure captures dropping as release returning to ground.",
    "pillars": [
      "solarpunk"
    ],
    "tags": [
      "Fundamental Actions & Movement",
      "Let Fall",
      "Let Something",
      "Release Downward",
      "Releasing Hold",
      "Gravity Taking",
      "Earth Surrender",
      "Letting Be"
    ]
  }
]