[
  {
    "word": "limera",
    "gloss": "shimmer",
    "ipa": "/li.ˈme.ra/",
    "syllables": [
      "li",
      "me",
      "ra"
    ],
    "pos": [
      "verb"
    ],
    "concept": "Shimmer / Gleam Wavering",
    "description": "To shine with a wavering light. Shimmering encompasses flickering radiance, dancing light, trembling glow, unstable brilliance.",
    "rationale": "The word 'limera' flows from light 'li' through flowing 'me' to radiant 'ra'. This light-flow-radiance pattern captures shimmering as light flowing into wavering radiance.",
    "pillars": [
      "art-nouveau"
    ],
    "tags": [
      "Fundamental Actions & Movement",
      "Gleam Wavering",
      "Wavering Light",
      "Shine Wavering",
      "Flickering Radiance",
      "Dancing Light",
      "Trembling Glow",
      "Unstable Brilliance"
    ]
  }
]