[
  {
    "word": "leu",
    "gloss": "acquaintance",
    "ipa": "/ˈle.u/",
    "syllables": [
      "le",
      "u"
    ],
    "pos": [
      "noun"
    ],
    "concept": "Acquaintance / A Friend Not Yet Known",
    "description": "One who is known by sight or name but not yet by heart. The relationship is one of gentle, surface-level connection with the potential for a deeper flow.",
    "rationale": "Composed from the established roots 'le' (gentle flow) and 'u' (potential, deep space). The word's structure suggests 'a potential for gentle flow.' This frames the relationship positively, as a precursor to deeper connection. Its simplicity and phonetic similarity to 'helu' (friendship) creates a poetic link between the two concepts.",
    "pillars": [
      "peace-linguistics-practices"
    ],
    "tags": [
      "social-role",
      "relationship-stage",
      "potential"
    ]
  }
]
